{
  "elements": [
    {
      "type": "magisterium:fold",
      "left": [
        {
          "type": "magisterium:heading",
          "text": {
            "translate": "magisterium.page.magisterium.cold_snap.heading",
            "font": "magisterium:small_caps"
          }
        },
        {
          "type": "magisterium:paragraph",
          "text": {
            "translate": "magisterium.page.magisterium.cold_snap.components"
          }
        },
        {
          "type": "magisterium:paragraph",
          "text": {
            "translate": "magisterium.page.magisterium.cold_snap.description.0"
          }
        },
        {
          "type": "magisterium:paragraph",
          "text": {
            "translate": "magisterium.page.magisterium.cold_snap.description.1"
          }
        }
      ],
      "right": [
        {
          "type": "magisterium:heading",
          "text": {
            "translate": "magisterium.page.magisterium.cold_snap.heading",
            "font": "magisterium:small_caps"
          }
        },
        {
          "type": "magisterium:inventory",
          "slots": [
            {
              "x": 33,
              "y": 0,
              "ingredient": "#magisterium:cold_snap_ingredients",
              "background": "magisterium:item/placeholder/question_mark"
            },
            {
              "x": 51,
              "y": 0,
              "ingredient": "#magisterium:cold_snap_ingredients",
              "background": "magisterium:item/placeholder/question_mark"
            },
            {
              "x": 42,
              "y": 18,
              "ingredient": "#magisterium:cold_snap_ingredients",
              "background": "magisterium:item/placeholder/question_mark"
            }
          ]
        },
        {
          "type": "magisterium:spell",
          "effect": "magisterium:cold_snap",
          "duration": 10,
          "text": {
            "translate": "magisterium.page.magisterium.cold_snap.spell",
            "font": "magisterium:small_caps"
          }
        }
      ]
    }
  ]
}